apprenti/__init__.py
apprenti-0.0.0.dist-info/METADATA
apprenti-0.0.0.dist-info/WHEEL
apprenti-0.0.0.dist-info/RECORD
