Metadata-Version: 2.3
Name: apprenti
Version: 0.0.0
Summary: Coming soon~
Author: Abdul Saleh
Requires-Python: >=3.12
Classifier: Programming Language :: Python :: 3
Classifier: Programming Language :: Python :: 3.12
Classifier: Programming Language :: Python :: 3.13
